openflow/__init__.py
openflow/datasource.py
openflow/openflow.py
openflow/transformer.py
openflow-0.1.2.4.dist-info/METADATA
openflow-0.1.2.4.dist-info/RECORD
openflow-0.1.2.4.dist-info/WHEEL
openflow-0.1.2.4.dist-info/top_level.txt
