Metadata-Version: 2.1
Name: openflow
Version: 0.1.2.4
Summary: Automate data flows for machine learning.
Home-page: http://github.com/shoprunback/openflow
Author: Quentin Lapointe
Author-email: quentin@shoprunback.com
License: MIT
Platform: UNKNOWN
Requires-Dist: numpy
Requires-Dist: pandas
Requires-Dist: scikit-learn
Requires-Dist: scipy
